{"credit":"Made with Blockbench","texture_size":[32,32],"textures":{"1":"void:void/void_colossus_helmet"},"elements":[{"from":[10.06868,22.5685,2],"to":[13.06868,26.5685,5],"rotation":{"angle":-45,"axis":"z","origin":[10.01942,24.57487,4.33744]},"faces":{"north":{"uv":[6,8,7.5,10],"texture":"#1"},"east":{"uv":[8,6,9.5,8],"texture":"#1"},"south":{"uv":[7.5,8,9,10],"texture":"#1"},"west":{"uv":[9,8,10.5,10],"texture":"#1"},"up":{"uv":[11,7.5,9.5,6],"texture":"#1"},"down":{"uv":[5.5,10,4,11.5],"texture":"#1"}}},{"from":[11.11041,23.50028,2.69712],"to":[13.11041,27.50028,4.69712],"rotation":{"angle":22.5,"axis":"x","origin":[10.01942,24.57487,4.33744]},"faces":{"north":{"uv":[10,4,11,6],"texture":"#1"},"east":{"uv":[5.5,10,6.5,12],"texture":"#1"},"south":{"uv":[6.5,10,7.5,12],"texture":"#1"},"west":{"uv":[7.5,10,8.5,12],"texture":"#1"},"up":{"uv":[11.5,10.5,10.5,9.5],"texture":"#1"},"down":{"uv":[11.5,10.5,10.5,11.5],"texture":"#1"}}},{"from":[11.61041,26.5484,2.25533],"to":[12.61041,29.5484,3.25533],"rotation":{"angle":45,"axis":"x","origin":[10.01942,24.57487,4.33744]},"faces":{"north":{"uv":[11,4,11.5,5.5],"texture":"#1"},"east":{"uv":[11,5.5,11.5,7],"texture":"#1"},"south":{"uv":[4,11.5,4.5,13],"texture":"#1"},"west":{"uv":[11.5,4,12,5.5],"texture":"#1"},"up":{"uv":[10,8,9.5,7.5],"texture":"#1"},"down":{"uv":[10.5,7.5,10,8],"texture":"#1"}}},{"from":[2.83132,18.5685,2],"to":[6.83132,22.5685,4],"rotation":{"angle":45,"axis":"z","origin":[5.88058,24.57487,4.33744]},"faces":{"north":{"uv":[4,8,6,10],"texture":"#1"},"east":{"uv":[8.5,10,9.5,12],"texture":"#1"},"south":{"uv":[8,4,10,6],"texture":"#1"},"west":{"uv":[9.5,10,10.5,12],"texture":"#1"},"up":{"uv":[12.5,8.5,10.5,7.5],"texture":"#1"},"down":{"uv":[12.5,8.5,10.5,9.5],"texture":"#1"}}},{"from":[2.83132,19.5685,3],"to":[6.83132,23.5685,5],"rotation":{"angle":45,"axis":"z","origin":[5.88058,25.57487,5.33744]},"faces":{"north":{"uv":[6,8,4,10],"texture":"#1"},"east":{"uv":[9.5,10,8.5,12],"texture":"#1"},"south":{"uv":[10,4,8,6],"texture":"#1"},"west":{"uv":[10.5,10,9.5,12],"texture":"#1"},"up":{"uv":[12.5,7.5,10.5,8.5],"texture":"#1"},"down":{"uv":[12.5,8.5,10.5,9.5],"texture":"#1"}}},{"from":[2.83132,22.5685,2],"to":[5.83132,26.5685,5],"rotation":{"angle":45,"axis":"z","origin":[5.88058,24.57487,4.33744]},"faces":{"north":{"uv":[7.5,8,6,10],"texture":"#1"},"east":{"uv":[10.5,8,9,10],"texture":"#1"},"south":{"uv":[9,8,7.5,10],"texture":"#1"},"west":{"uv":[9.5,6,8,8],"texture":"#1"},"up":{"uv":[11,6,9.5,7.5],"texture":"#1"},"down":{"uv":[5.5,10,4,11.5],"texture":"#1"}}},{"from":[2.78959,23.50028,2.69712],"to":[4.78959,27.50028,4.69712],"rotation":{"angle":22.5,"axis":"x","origin":[5.88058,24.57487,4.33744]},"faces":{"north":{"uv":[11,4,10,6],"texture":"#1"},"east":{"uv":[8.5,10,7.5,12],"texture":"#1"},"south":{"uv":[7.5,10,6.5,12],"texture":"#1"},"west":{"uv":[6.5,10,5.5,12],"texture":"#1"},"up":{"uv":[11.5,9.5,10.5,10.5],"texture":"#1"},"down":{"uv":[11.5,10.5,10.5,11.5],"texture":"#1"}}},{"from":[3.28959,26.5484,2.25533],"to":[4.28959,29.5484,3.25533],"rotation":{"angle":45,"axis":"x","origin":[5.88058,24.57487,4.33744]},"faces":{"north":{"uv":[11.5,4,11,5.5],"texture":"#1"},"east":{"uv":[12,4,11.5,5.5],"texture":"#1"},"south":{"uv":[4.5,11.5,4,13],"texture":"#1"},"west":{"uv":[11.5,5.5,11,7],"texture":"#1"},"up":{"uv":[10,7.5,9.5,8],"texture":"#1"},"down":{"uv":[10.5,7.5,10,8],"texture":"#1"}}},{"name":"head","from":[3.4,14.8,3.4],"to":[12.6,24,12.6],"rotation":{"angle":0,"axis":"y","origin":[8,-8,8]},"faces":{"north":{"uv":[0,0,4,4],"texture":"#1"},"east":{"uv":[0,4,4,8],"texture":"#1"},"south":{"uv":[4,0,8,4],"texture":"#1"},"west":{"uv":[4,4,8,8],"texture":"#1"},"up":{"uv":[4,12,0,8],"texture":"#1"},"down":{"uv":[12,0,8,4],"texture":"#1"}}}],"gui_light":"front","display":{"thirdperson_righthand":{"rotation":[45,0,0],"translation":[0,-3.25,-8.75],"scale":[0.75,0.75,0.75]},"thirdperson_lefthand":{"rotation":[45,0,0],"translation":[0,-3.25,-7.25],"scale":[0.75,0.75,0.75]},"firstperson_righthand":{"rotation":[-25,0,0],"translation":[-0.25,-3.75,4],"scale":[0.75,0.75,0.75]},"firstperson_lefthand":{"rotation":[-25,0,0],"translation":[-0.25,-3.75,4],"scale":[0.75,0.75,0.75]},"ground":{"translation":[0,-6.5,0],"scale":[0.75,0.75,0.75]},"gui":{"rotation":[0,180,0],"translation":[0,-9.75,0],"scale":[0.75,0.75,0.75]},"head":{"translation":[0,-16.25,0],"scale":[1.5,1.5,1.5]},"fixed":{"translation":[0,-13,0]}},"groups":[{"name":"group","origin":[8,8,8],"color":0,"children":[{"name":"group","origin":[12.01041,26.67487,3.2],"color":0,"children":[0,1,2]},{"name":"group","origin":[12.01041,26.67487,3.2],"color":0,"children":[3,4,5,6,7]},8]}]}